scalar_ninja/__init__.py
scalar_ninja/py.typed
scalar_ninja/scalar_ninja.py
scalar_ninja-0.1.1.dist-info/METADATA
scalar_ninja-0.1.1.dist-info/WHEEL
scalar_ninja-0.1.1.dist-info/top_level.txt
scalar_ninja-0.1.1.dist-info/RECORD
